conda_resolvelib_solver/_version.py
conda_resolvelib_solver/plugin.py
conda_resolvelib_solver/solver.py
conda_resolvelib_solver-0.1.dist-info/licenses/LICENSE
conda_resolvelib_solver-0.1.dist-info/METADATA
conda_resolvelib_solver-0.1.dist-info/WHEEL
conda_resolvelib_solver-0.1.dist-info/entry_points.txt
conda_resolvelib_solver-0.1.dist-info/top_level.txt
conda_resolvelib_solver-0.1.dist-info/RECORD
