Metadata-Version: 2.4
Name: conda-resolvelib-solver
Version: 0.1
Summary: Resolvelib based conda solver
Author-email: "Jonathan J. Helmus" <jjhelmus@gmail.com>
License-Expression: BSD-3-Clause
Project-URL: homepage, https://github.com/jjhelmus/conda-resolvelib-solver
Classifier: Programming Language :: Python :: 3
Classifier: Programming Language :: Python :: 3 :: Only
Classifier: Programming Language :: Python :: 3.9
Classifier: Programming Language :: Python :: 3.10
Classifier: Programming Language :: Python :: 3.11
Classifier: Programming Language :: Python :: 3.12
Classifier: Programming Language :: Python :: 3.13
Classifier: Programming Language :: Python :: Implementation :: CPython
Classifier: Programming Language :: Python :: Implementation :: PyPy
Requires-Python: >=3.9
License-File: LICENSE
Requires-Dist: conda>=23.7.3
Requires-Dist: resolvelib
Requires-Dist: boltons>=23.0.0
Dynamic: license-file
